liccheck/command_line.py
liccheck2-0.1.4.dist-info/DESCRIPTION.rst
liccheck2-0.1.4.dist-info/METADATA
liccheck2-0.1.4.dist-info/RECORD
liccheck2-0.1.4.dist-info/WHEEL
liccheck2-0.1.4.dist-info/entry_points.txt
liccheck2-0.1.4.dist-info/metadata.json
liccheck2-0.1.4.dist-info/top_level.txt
