Metadata-Version: 2.0
Name: liccheck2
Version: 0.1.4
Summary: Check python packages from requirement.txt and report issues
Home-page: https://github.com/dhatim/python-license-check
Author: Dhatim
Author-email: msauvee@dhatim.com
License: Apache Software License
Keywords: license check build tool
Platform: UNKNOWN
Classifier: Development Status :: 5 - Production/Stable
Classifier: Intended Audience :: Developers
Classifier: Topic :: Software Development :: Build Tools
Classifier: License :: OSI Approved :: Apache Software License
Classifier: Programming Language :: Python :: 3
Classifier: Programming Language :: Python :: 3.3
Classifier: Programming Language :: Python :: 3.4
Classifier: Programming Language :: Python :: 3.5
Requires-Python: >=3
Requires-Dist: argparse
Requires-Dist: configparser
